jarvion/__init__.py
jarvion-1.0.1.dist-info/METADATA
jarvion-1.0.1.dist-info/WHEEL
jarvion-1.0.1.dist-info/top_level.txt
jarvion-1.0.1.dist-info/RECORD
