Metadata-Version: 2.2
Name: jarvion
Version: 1.0.1
Author: Salman Developer
Author-email: salmanfareedchishty135@gmail.com
Dynamic: author
Dynamic: author-email
Dynamic: description
Dynamic: description-content-type
